Decoder_2to4/decoder_2to4.v
module decoder_2to4 (
    input wire [1:0]in,
    input wire enable,
    output reg [3:0]out
);
    always @(*) begin
        if (enable) begin
            case (in)
            2'b00: out = 4'b1110;
            2'b01: out = 4'b1101;
            2'b10: out = 4'b1011;
            2'b11: out = 4'b0111;
            default: out = 4'b1111;
            endcase
        end
        else begin
            out = 4'b1111;
        end
    end    
endmodule

Decoder_3to8/decoder_3to8.v
`include "/home/inish/Data/VerilogHardware/Decoder_2to4/decoder_2to4.v"

module decoder_3to8 (
    input wire [2:0] in,
    input wire enable,
    output wire [7:0] out
);
    wire [3:0] out_low, out_high;

    decoder_2to4 dec1 (
        .in(in[1:0]), 
        .enable(~in[2] & enable), 
        .out(out_low)
    );

    decoder_2to4 dec2 (
        .in(in[1:0]), 
        .enable(in[2] & enable), 
        .out(out_high)
    );

    assign out = {out_high, out_low};
    
endmodule

Decoder_3to8/decoder_3to8_tb.v
module decoder_3to8_tb;
    reg [2:0] in;   
    reg enable;   
    wire [7:0] out;  

    decoder_3to8 uut (
        .in(in),
        .enable(enable),
        .out(out)
    );

    initial begin
        $dumpfile("decoder_3to8_tb.vcd");
        $dumpvars(0, decoder_3to8_tb);
        $monitor("Time=%0t | Enable=%b | in=%b | out=%b", $time, enable, in, out);
        
        enable = 0; in = 3'b000; #10;  
        enable = 1; in = 3'b000; #10;  
        enable = 1; in = 3'b001; #10; 
        enable = 1; in = 3'b010; #10; 
        enable = 1; in = 3'b011; #10; 
        enable = 1; in = 3'b100; #10;  
        enable = 1; in = 3'b101; #10;  
        enable = 1; in = 3'b110; #10;  
        enable = 1; in = 3'b111; #10;  
        enable = 0; in = 3'b101; #10;  
        $stop;
    end
endmodule

Decoder_3to8/decoder_3to8_tb.vcd
$date
	Thu Mar 20 00:44:45 2025
$end
$version
	Icarus Verilog
$end
$timescale
	1s
$end
$scope module decoder_3to8_tb $end
$var wire 8 ! out [7:0] $end
$var reg 1 " enable $end
$var reg 3 # in [2:0] $end
$scope module uut $end
$var wire 1 " enable $end
$var wire 3 $ in [2:0] $end
$var wire 4 % out_low [3:0] $end
$var wire 4 & out_high [3:0] $end
$var wire 8 ' out [7:0] $end
$scope module dec1 $end
$var wire 1 ( enable $end
$var wire 2 ) in [1:0] $end
$var reg 4 * out [3:0] $end
$upscope $end
$scope module dec2 $end
$var wire 1 + enable $end
$var wire 2 , in [1:0] $end
$var reg 4 - out [3:0] $end
$upscope $end
$upscope $end
$upscope $end
$enddefinitions $end
$comment Show the parameter values. $end
$dumpall
$end
#0
$dumpvars
b1111 -
b0 ,
0+
b1111 *
b0 )
0(
b11111111 '
b1111 &
b1111 %
b0 $
b0 #
0"
b11111111 !
$end
#10
b11111110 !
b11111110 '
b1110 %
b1110 *
1(
1"
#20
b11111101 !
b11111101 '
b1101 %
b1101 *
b1 )
b1 ,
b1 #
b1 $
#30
b11111011 !
b11111011 '
b1011 %
b1011 *
b10 )
b10 ,
b10 #
b10 $
#40
b11110111 !
b11110111 '
b111 %
b111 *
b11 )
b11 ,
b11 #
b11 $
#50
0(
b11101111 !
b11101111 '
b1111 %
b1111 *
b1110 &
b1110 -
1+
b0 )
b0 ,
b100 #
b100 $
#60
b11011111 !
b11011111 '
b1101 &
b1101 -
b1 )
b1 ,
b101 #
b101 $
#70
b10111111 !
b10111111 '
b1011 &
b1011 -
b10 )
b10 ,
b110 #
b110 $
#80
b1111111 !
b1111111 '
b111 &
b111 -
b11 )
b11 ,
b111 #
b111 $
#90
b11111111 !
b11111111 '
b1111 &
b1111 -
b1 )
b1 ,
0+
b101 #
b101 $
0"
