Mux_2to1/Mux_2to1.v
module mux_2to1 (
    input wire a,     
    input wire b,     
    input wire sel,   
    output wire y     
);
    assign y = (sel) ? b : a; 
endmodule

Mux_2to1/Mux_2to1_tb.v
module mux_2to1_tb;
    reg t_a, t_b, t_sel;
    wire t_y;          
    
    mux_2to1 uut (.a(t_a), .b(t_b), .sel(t_sel), .y(t_y));

    initial begin
        $dumpfile("mux_2to1_tb.vcd");
        $dumpvars(0, mux_2to1_tb);
        t_a = 0; t_b = 0; t_sel = 0; #10;
        t_a = 0; t_b = 1; t_sel = 0; #10;
        t_a = 1; t_b = 0; t_sel = 0; #10;
        t_a = 1; t_b = 1; t_sel = 0; #10;

        t_a = 0; t_b = 0; t_sel = 1; #10;
        t_a = 0; t_b = 1; t_sel = 1; #10;
        t_a = 1; t_b = 0; t_sel = 1; #10;
        t_a = 1; t_b = 1; t_sel = 1; #10;
        $stop;
    end
endmodule

Mux_2to1/mux_2to1_tb.vcd
$date
	Tue Mar 11 01:04:37 2025
$end
$version
	Icarus Verilog
$end
$timescale
	1s
$end
$scope module mux_2to1_tb $end
$var wire 1 ! t_y $end
$var reg 1 " t_a $end
$var reg 1 # t_b $end
$var reg 1 $ t_sel $end
$scope module uut $end
$var wire 1 " a $end
$var wire 1 # b $end
$var wire 1 $ sel $end
$var wire 1 ! y $end
$upscope $end
$upscope $end
$enddefinitions $end
$comment Show the parameter values. $end
$dumpall
$end
#0
$dumpvars
0$
0#
0"
0!
$end
#10
1#
#20
1!
0#
1"
#30
1#
#40
0!
1$
0#
0"
#50
1!
1#
#60
0!
0#
1"
#70
1!
1#
