Mux_2to1/Mux_2to1.v
module mux_2to1 (
    input wire a,     
    input wire b,     
    input wire sel,   
    output wire y     
);
    assign y = (sel) ? b : a; 
endmodule

Mux_4to1/mux_4to1.v
module mux_4to1 (
    input wire [1:0] sel,
    input wire [3:0] in,
    output reg out
);
    always @(*)
    begin
        case (sel)
            2'b00: out = in[0];
            2'b01: out = in[1];
            2'b10: out = in[2];
            2'b11: out = in[3];
            default: out = 0;
        endcase
    end
endmodule

Mux_8to1/mux_8to1.v
`include "/home/inish/Data/VerilogHardware/Mux_4to1/mux_4to1.v"  
`include "/home/inish/Data/VerilogHardware/Mux_2to1/Mux_2to1.v" 

module mux_8to1 (
    input wire [2:0] sel,   
    input wire [7:0] in,   
    output wire out         
);
    wire out1, out2;  

    mux_4to1 mux1 (
        .sel(sel[1:0]), 
        .in(in[3:0]), 
        .out(out1)
    );

    mux_4to1 mux2 (
        .sel(sel[1:0]), 
        .in(in[7:4]), 
        .out(out2)
    );

    mux_2to1 mux3 (
        .a(out1), 
        .b(out2), 
        .sel(sel[2]), 
        .y(out)
    );
endmodule

Mux_8to1/mux_8to1_tb.v
module mux_8to1_tb;
    reg [2:0] sel;
    reg [7:0] in;
    wire out;

    mux_8to1 uut (
        .sel(sel),
        .in(in),
        .out(out)
    );

    initial begin
        $dumpfile("mux_8to1_tb.vcd");
        $dumpvars(0, mux_8to1_tb);
        $monitor("Time = %0t | sel = %b | in = %b | out = %b", $time, sel, in, out);

        in = 8'b10110011;

        sel = 3'b000; #10;
        sel = 3'b001; #10;
        sel = 3'b010; #10;
        sel = 3'b011; #10;
        sel = 3'b100; #10;
        sel = 3'b101; #10;
        sel = 3'b110; #10;
        sel = 3'b111; #10;
        $stop;
    end
endmodule

Mux_8to1/mux_8to1_tb.vcd
$date
	Mon Mar 17 19:19:05 2025
$end
$version
	Icarus Verilog
$end
$timescale
	1s
$end
$scope module mux_8to1_tb $end
$var wire 1 ! out $end
$var reg 8 " in [7:0] $end
$var reg 3 # sel [2:0] $end
$scope module uut $end
$var wire 8 $ in [7:0] $end
$var wire 3 % sel [2:0] $end
$var wire 1 & out2 $end
$var wire 1 ' out1 $end
$var wire 1 ! out $end
$scope module mux1 $end
$var wire 4 ( in [3:0] $end
$var wire 2 ) sel [1:0] $end
$var reg 1 ' out $end
$upscope $end
$scope module mux2 $end
$var wire 4 * in [3:0] $end
$var wire 2 + sel [1:0] $end
$var reg 1 & out $end
$upscope $end
$scope module mux3 $end
$var wire 1 ' a $end
$var wire 1 & b $end
$var wire 1 , sel $end
$var wire 1 ! y $end
$upscope $end
$upscope $end
$upscope $end
$enddefinitions $end
$comment Show the parameter values. $end
$dumpall
$end
#0
$dumpvars
0,
b0 +
b1011 *
b0 )
b11 (
1'
1&
b0 %
b10110011 $
b0 #
b10110011 "
1!
$end
#10
b1 )
b1 +
b1 #
b1 %
#20
0!
0'
0&
b10 )
b10 +
b10 #
b10 %
#30
1&
b11 )
b11 +
b11 #
b11 %
#40
1'
1!
b0 )
b0 +
1,
b100 #
b100 %
#50
b1 )
b1 +
b101 #
b101 %
#60
0!
0'
0&
b10 )
b10 +
b110 #
b110 %
#70
1!
1&
b11 )
b11 +
b111 #
b111 %
