Full_Adder/full_adder.v
module full_adder(
    a,b,c,s,carry
);
    input a,b,c;
    output s,carry;
    assign s=a^b^c;
    assign carry=(a&b)+(b&c)+(a&c);
endmodule

Full_Adder/full_adder_tb.v
module full_adder_tb();
    reg t_a,t_b,t_c;
    wire SUM,CARRY_OUT;

    full_adder dut(.a(t_a),.b(t_b),.c(t_c),.s(SUM),.carry(CARRY_OUT));

    initial begin
        $dumpfile("full_adder_tb.vcd");
        $dumpvars(0, full_adder_tb);
        t_a=0;t_b=0;t_c=0;
        #10
        t_a=0;t_b=0;t_c=1;
        #10
        t_a=0;t_b=1;t_c=0;
        #10
        t_a=0;t_b=1;t_c=1;
        #10
        t_a=1;t_b=0;t_c=0;
        #10
        t_a=1;t_b=0;t_c=1;
        #10
        t_a=1;t_b=1;t_c=0;
        #10
        t_a=1;t_b=1;t_c=1;
        #10
        $stop;
    end
endmodule

Full_Adder/full_adder_tb.vcd
$date
	Mon Mar 10 19:19:17 2025
$end
$version
	Icarus Verilog
$end
$timescale
	1s
$end
$scope module full_adder_tb $end
$var wire 1 ! SUM $end
$var wire 1 " CARRY_OUT $end
$var reg 1 # t_a $end
$var reg 1 $ t_b $end
$var reg 1 % t_c $end
$scope module dut $end
$var wire 1 # a $end
$var wire 1 $ b $end
$var wire 1 % c $end
$var wire 1 ! s $end
$var wire 1 " carry $end
$upscope $end
$upscope $end
$enddefinitions $end
$comment Show the parameter values. $end
$dumpall
$end
#0
$dumpvars
0%
0$
0#
0"
0!
$end
#10
1!
1%
#20
0%
1$
#30
0!
1"
1%
#40
1!
0"
0%
0$
1#
#50
0!
1"
1%
#60
1"
0%
1$
#70
1!
1"
1%
